setup.py
libvmware/AllVMs.py
libvmware/Cli.py
libvmware/Clone.py
libvmware/Config.py
libvmware/ManageVM.py
libvmware/Tasks.py
libvmware/VMInfo.py
libvmware/__init__.py
libvmware/vCenterConnect.py
libvmware.egg-info/PKG-INFO
libvmware.egg-info/SOURCES.txt
libvmware.egg-info/dependency_links.txt
libvmware.egg-info/not-zip-safe
libvmware.egg-info/requires.txt
libvmware.egg-info/top_level.txt