Metadata-Version: 1.0
Name: libvmware
Version: 0.1
Summary: Simple library for working with VMWare
Home-page: UNKNOWN
Author: Austin Simmons
Author-email: austin@simmons-tech.net
License: UNKNOWN
Platform: UNKNOWN
